djangounittest/__init__.py
djangounittest/mainunittest.py
djangounittest-0.2.4.dist-info/METADATA
djangounittest-0.2.4.dist-info/WHEEL
djangounittest-0.2.4.dist-info/top_level.txt
djangounittest-0.2.4.dist-info/RECORD
