Metadata-Version: 2.1
Name: djangounittest
Version: 0.2.4
Summary: A django testing framework
Home-page: UNKNOWN
Author: NeuralNine (Florian Dedov)
Author-email: <djangouniittest@gmail.com>
License: UNKNOWN
Keywords: python,test,Django
Platform: UNKNOWN
Classifier: Development Status :: 1 - Planning
Classifier: Intended Audience :: Developers
Classifier: Programming Language :: Python :: 3
Classifier: Operating System :: Unix
Classifier: Operating System :: MacOS :: MacOS X
Classifier: Operating System :: Microsoft :: Windows
